trivia/__init__.py
trivia/__main__.py
trivia/client.py
trivia.py-1.0.8.dist-info/METADATA
trivia.py-1.0.8.dist-info/WHEEL
trivia.py-1.0.8.dist-info/top_level.txt
trivia.py-1.0.8.dist-info/RECORD
