Metadata-Version: 2.1
Name: trivia.py
Version: 1.0.8
Summary: A python wrapper for Open Trivia DB
Home-page: https://github.com/Epicyon-H/trivia.py
Author: Epicyon
License: MIT
Platform: UNKNOWN
Classifier: License :: OSI Approved :: MIT License
Classifier: Programming Language :: Python :: 3.6
Classifier: Programming Language :: Python :: 3.7
Classifier: Programming Language :: Python :: 3.8
Requires-Dist: aiohttp
Requires-Dist: aiodns
